guarantor/__init__.py
guarantor/__main__.py
guarantor/main.py
guarantor/models.py
guarantor-2022.1001a0.dist-info/LICENSE
guarantor-2022.1001a0.dist-info/METADATA
guarantor-2022.1001a0.dist-info/WHEEL
guarantor-2022.1001a0.dist-info/entry_points.txt
guarantor-2022.1001a0.dist-info/top_level.txt
guarantor-2022.1001a0.dist-info/zip-safe
guarantor-2022.1001a0.dist-info/RECORD
