Metadata-Version: 2.1
Name: guarantor
Version: 2022.1001a0
Summary: The Guarantor Project.
Home-page: https://github.com/xkudev/guarantor
Author: xkudev
Author-email: xkudev@pm.me
License: MIT
Keywords: guarantor
Classifier: Development Status :: 3 - Alpha
Classifier: Environment :: Console
Classifier: Environment :: Other Environment
Classifier: Intended Audience :: Developers
Classifier: License :: OSI Approved :: MIT License
Classifier: Operating System :: Unix
Classifier: Operating System :: POSIX
Classifier: Operating System :: MacOS :: MacOS X
Classifier: Programming Language :: Python
Classifier: Programming Language :: Python :: 3
Classifier: Programming Language :: Python :: Implementation :: CPython
Classifier: Programming Language :: Python :: Implementation :: PyPy
Classifier: Topic :: Software Development :: Libraries
Classifier: Topic :: Software Development :: Libraries :: Python Modules
Requires-Python: >=3.10
License-File: LICENSE
Requires-Dist: fastapi (==0.78.0)
Requires-Dist: orjson (==3.7.1)
Requires-Dist: jinja2 (==3.1.2)
Requires-Dist: pydantic[email] (==1.9.1)
Requires-Dist: uvicorn[standard] (==0.17.6)
Requires-Dist: SQLAlchemy (==1.4.37)
Requires-Dist: cryptography (==37.0.2)
